pirate/chains/__init__.py
pirate/chains/base.py
pirate/chains/mine_chain.py
pirate/data/__init__.py
pirate/data/base.py
pirate/data/passages.py
pirate/data/queries.py
pirate/data/ranking.py
pirate/data/triples.py
pirate/miner/base.py
pirate/miner/hard_neg.py
pirate/miner/in_batch_neg.py
pirate/models/__init__.py
pirate/models/chains.py
pirate/models/mining.py
pirate/models/types.py
pirate/retrievers/__init__.py
pirate/retrievers/base.py
pirate/retrievers/bi_encoder.py
pirate/retrievers/bm25.py
pirate/retrievers/cross_encoder.py
pirate-0.1.1a1.dist-info/LICENSE
pirate-0.1.1a1.dist-info/METADATA
pirate-0.1.1a1.dist-info/WHEEL
pirate-0.1.1a1.dist-info/RECORD
