Metadata-Version: 2.1
Name: pirate
Version: 0.1.1a1
Summary: Pirate is a Python package that aims to be a unified framework for all things information retrieval. Currently, it serves as a go-to library for negative mining.
Author: Herumb Shandilya
Author-email: herumbshandilya123@gmail.com
Requires-Python: >=3.10,<4.0
Classifier: Programming Language :: Python :: 3
Classifier: Programming Language :: Python :: 3.10
Classifier: Programming Language :: Python :: 3.11
Classifier: Programming Language :: Python :: 3.12
Requires-Dist: loguru (>=0.7.2,<0.8.0)
Requires-Dist: mkdocs-material[imaging] (>=9.5.14,<10.0.0)
Requires-Dist: mkdocstrings[crystal,python] (>=0.24.1,<0.25.0)
Requires-Dist: polars (>=0.20.16,<0.21.0)
Requires-Dist: pydantic (>=2.7.1,<3.0.0)
Requires-Dist: pyright (>=1.1.362,<2.0.0)
Requires-Dist: pytest (>=8.1.1,<9.0.0)
Requires-Dist: rank-bm25 (>=0.2.2,<0.3.0)
Requires-Dist: ruff (>=0.4.4,<0.5.0)
Requires-Dist: sentence-transformers (>=2.6.1,<3.0.0)
